excelsheet_to_mysqldatabasetable/__init__.py
excelsheet_to_mysqldatabasetable/excel_converter.py
excelsheet_to_mysqldatabasetable-2.4.0.dist-info/METADATA
excelsheet_to_mysqldatabasetable-2.4.0.dist-info/WHEEL
excelsheet_to_mysqldatabasetable-2.4.0.dist-info/top_level.txt
excelsheet_to_mysqldatabasetable-2.4.0.dist-info/RECORD
