Metadata-Version: 2.1
Name: excelsheet-to-mysqldatabasetable
Version: 2.4.0
Summary: An  API that allows you to convert/transfer the data in the ExcelSheet to a Table in the Mysql Database
Home-page: https://github.com/odiwuorlameck2019gmail
Author: Odiwuor Lameck
Author-email: odiwuorlameck2019@gmail.com
License: MIT
Platform: UNKNOWN
Classifier: License :: OSI Approved :: MIT License
Classifier: Programming Language :: Python
Classifier: Programming Language :: Python :: 3
Classifier: Programming Language :: Python :: 3.6
Classifier: Programming Language :: Python :: Implementation :: CPython
Classifier: Programming Language :: Python :: Implementation :: PyPy
Requires-Python: >=3.6.0
Requires-Dist: pandas
Requires-Dist: mysql.connector
Requires-Dist: openpyxl
